{
  "spotify_track_id": "32hCVyTsvtyQAcpPDgP3Rk",
  "difficulty": "normal",
  "name": "Default",
  "duration_s": 150.016,
  "bpm": 129.2,
  "version": 1,
  "seed": 31,
  "score": {
    "total": 9.54,
    "beat_sync": 10.0,
    "flow": 9.28,
    "difficulty_curve": 9.33,
    "type_variety": 9.76,
    "lane_coverage": 10.0,
    "energy_match": 8.11,
    "cull_rate": 10.0
  },
  "attempts": 31,
  "events": [
    {
      "t": 18.808,
      "lane": 0,
      "type": "pickup_ammo"
    },
    {
      "t": 20.689,
      "lane": 0,
      "type": "car"
    },
    {
      "t": 31.927,
      "lane": 0,
      "type": "crash"
    },
    {
      "t": 31.927,
      "lane": 1,
      "type": "car"
    },
    {
      "t": 32.996,
      "lane": 1,
      "type": "crash"
    },
    {
      "t": 45.341,
      "lane": 3,
      "type": "guardian"
    },
    {
      "t": 46.115,
      "lane": 3,
      "type": "pickup_ammo"
    },
    {
      "t": 47.067,
      "lane": 2,
      "type": "car"
    },
    {
      "t": 51.757,
      "lane": 3,
      "type": "crash"
    },
    {
      "t": 53.979,
      "lane": 2,
      "type": "guardian"
    },
    {
      "t": 54.567,
      "lane": 2,
      "type": "pickup_ammo"
    },
    {
      "t": 67.222,
      "lane": 3,
      "type": "enemy_car"
    },
    {
      "t": 71.308,
      "lane": 2,
      "type": "car_crash_beat",
      "lead": 1.182
    },
    {
      "t": 73.189,
      "lane": 2,
      "type": "car"
    },
    {
      "t": 73.189,
      "lane": 1,
      "type": "car_crash_beat",
      "lead": 1.19
    },
    {
      "t": 74.118,
      "lane": 1,
      "type": "pickup_ammo"
    },
    {
      "t": 75.047,
      "lane": 1,
      "type": "car"
    },
    {
      "t": 75.999,
      "lane": 0,
      "type": "slow"
    },
    {
      "t": 83.638,
      "lane": 0,
      "type": "car"
    },
    {
      "t": 87.864,
      "lane": 1,
      "type": "enemy_car"
    },
    {
      "t": 91.434,
      "lane": 2,
      "type": "guardian"
    },
    {
      "t": 92.09,
      "lane": 2,
      "type": "pickup_ammo"
    },
    {
      "t": 93.971,
      "lane": 2,
      "type": "crash"
    },
    {
      "t": 101.448,
      "lane": 3,
      "type": "pickup_ammo"
    },
    {
      "t": 103.306,
      "lane": 3,
      "type": "crash"
    },
    {
      "t": 106.115,
      "lane": 3,
      "type": "slow"
    },
    {
      "t": 107.067,
      "lane": 1,
      "type": "pickup_ammo"
    },
    {
      "t": 107.996,
      "lane": 2,
      "type": "crash"
    },
    {
      "t": 109.877,
      "lane": 1,
      "type": "slow"
    },
    {
      "t": 110.829,
      "lane": 0,
      "type": "crash"
    },
    {
      "t": 111.758,
      "lane": 3,
      "type": "pickup_ammo"
    },
    {
      "t": 113.615,
      "lane": 0,
      "type": "crash"
    },
    {
      "t": 114.567,
      "lane": 1,
      "type": "car"
    },
    {
      "t": 117.377,
      "lane": 2,
      "type": "crash"
    },
    {
      "t": 118.306,
      "lane": 0,
      "type": "pickup_ammo"
    },
    {
      "t": 121.139,
      "lane": 3,
      "type": "slow"
    },
    {
      "t": 122.067,
      "lane": 3,
      "type": "slow"
    },
    {
      "t": 122.613,
      "lane": 2,
      "type": "guardian"
    },
    {
      "t": 122.996,
      "lane": 2,
      "type": "pickup_ammo"
    },
    {
      "t": 124.877,
      "lane": 2,
      "type": "crash"
    },
    {
      "t": 125.829,
      "lane": 1,
      "type": "crash"
    },
    {
      "t": 126.758,
      "lane": 0,
      "type": "slow"
    },
    {
      "t": 127.105,
      "lane": 1,
      "type": "guardian"
    },
    {
      "t": 127.687,
      "lane": 1,
      "type": "pickup_ammo"
    },
    {
      "t": 128.615,
      "lane": 0,
      "type": "crash"
    },
    {
      "t": 129.567,
      "lane": 2,
      "type": "pickup_shield"
    },
    {
      "t": 130.496,
      "lane": 1,
      "type": "car_crash_beat",
      "lead": 1.182
    },
    {
      "t": 132.377,
      "lane": 1,
      "type": "car"
    },
    {
      "t": 133.306,
      "lane": 2,
      "type": "car"
    },
    {
      "t": 135.21,
      "lane": 3,
      "type": "crash"
    },
    {
      "t": 135.485,
      "lane": 3,
      "type": "guardian"
    },
    {
      "t": 136.139,
      "lane": 3,
      "type": "pickup_ammo"
    },
    {
      "t": 138.809,
      "lane": 3,
      "type": "car"
    },
    {
      "t": 139.738,
      "lane": 2,
      "type": "car"
    },
    {
      "t": 140.666,
      "lane": 1,
      "type": "car_crash_beat",
      "lead": 1.182
    },
    {
      "t": 142.547,
      "lane": 1,
      "type": "car"
    },
    {
      "t": 143.499,
      "lane": 0,
      "type": "pickup_shield"
    },
    {
      "t": 147.238,
      "lane": 0,
      "type": "slow"
    }
  ]
}